pypi_install/__init__.py
pypi_install/pypi_install.py
pypi_install-0.0.5.dist-info/METADATA
pypi_install-0.0.5.dist-info/RECORD
pypi_install-0.0.5.dist-info/WHEEL
pypi_install-0.0.5.dist-info/top_level.txt
