Metadata-Version: 2.1
Name: pypi_install
Version: 0.0.5
Summary: Uploading code to PyPi made easy
Home-page: https://github.com/daroodar/Pypi-Install
Author: Osama Arshad Dar
Author-email: 14beeodar@seecs.edu.pk
License: UNKNOWN
Platform: UNKNOWN
Classifier: Programming Language :: Python :: 2
Classifier: License :: OSI Approved :: MIT License
Classifier: Operating System :: OS Independent
